LICENSE
README.md
setup.py
gAIRR_suite/__init__.py
gAIRR_suite/gAIRR_annotate.py
gAIRR_suite/gAIRR_call.py
gAIRR_suite.egg-info/PKG-INFO
gAIRR_suite.egg-info/SOURCES.txt
gAIRR_suite.egg-info/dependency_links.txt
gAIRR_suite.egg-info/entry_points.txt
gAIRR_suite.egg-info/not-zip-safe
gAIRR_suite.egg-info/requires.txt
gAIRR_suite.egg-info/top_level.txt
gAIRR_suite/material/BCRD_alleles_parsed.fasta
gAIRR_suite/material/BCRD_plusHep_alleles_parsed.fasta
gAIRR_suite/material/BCRD_plusHep_alleles_parsed.fasta.amb
gAIRR_suite/material/BCRD_plusHep_alleles_parsed.fasta.ann
gAIRR_suite/material/BCRD_plusHep_alleles_parsed.fasta.bwt
gAIRR_suite/material/BCRD_plusHep_alleles_parsed.fasta.pac
gAIRR_suite/material/BCRD_plusHep_alleles_parsed.fasta.sa
gAIRR_suite/material/BCRJ_alleles_parsed.fasta
gAIRR_suite/material/BCRJ_alleles_parsed.fasta.amb
gAIRR_suite/material/BCRJ_alleles_parsed.fasta.ann
gAIRR_suite/material/BCRJ_alleles_parsed.fasta.bwt
gAIRR_suite/material/BCRJ_alleles_parsed.fasta.pac
gAIRR_suite/material/BCRJ_alleles_parsed.fasta.sa
gAIRR_suite/material/BCRV_alleles.fasta
gAIRR_suite/material/BCRV_alleles_parsed.fasta
gAIRR_suite/material/BCRV_alleles_parsed.fasta.amb
gAIRR_suite/material/BCRV_alleles_parsed.fasta.ann
gAIRR_suite/material/BCRV_alleles_parsed.fasta.bwt
gAIRR_suite/material/BCRV_alleles_parsed.fasta.fai
gAIRR_suite/material/BCRV_alleles_parsed.fasta.pac
gAIRR_suite/material/BCRV_alleles_parsed.fasta.sa
gAIRR_suite/material/HG001_IGHV_annotation.txt
gAIRR_suite/material/IGHV3-30_genes_rename.fasta
gAIRR_suite/material/IGHV_functional.txt
gAIRR_suite/material/IGH_functional.txt
gAIRR_suite/material/IGJ.txt
gAIRR_suite/material/IGKV_functional.txt
gAIRR_suite/material/IGLV_functional.txt
gAIRR_suite/material/IG_RSS.fasta
gAIRR_suite/material/IG_heptamer_nonamer.fasta
gAIRR_suite/material/TCRD_alleles_parsed.fasta
gAIRR_suite/material/TCRD_plusHep_alleles_parsed.fasta
gAIRR_suite/material/TCRD_plusHep_alleles_parsed.fasta.amb
gAIRR_suite/material/TCRD_plusHep_alleles_parsed.fasta.ann
gAIRR_suite/material/TCRD_plusHep_alleles_parsed.fasta.bwt
gAIRR_suite/material/TCRD_plusHep_alleles_parsed.fasta.pac
gAIRR_suite/material/TCRD_plusHep_alleles_parsed.fasta.sa
