Metadata-Version: 2.4
Name: gAIRR_suite
Version: 0.3.3
Summary: Profiling genes encoding the adaptive immune receptor repertoire with gAIRR Suite.
Home-page: https://github.com/maojanlin/gAIRRsuite
Download-URL: https://github.com/maojanlin/gAIRRsuite/tarball/master
Author: Mao-Jan Lin
Author-email: mj.maojanlin@gmail.com
License: MIT
Keywords: AIRR,annotation,allele typing,novel allele
Classifier: Development Status :: 3 - Alpha
Classifier: Intended Audience :: Developers
Classifier: Topic :: Software Development :: Build Tools
Classifier: License :: OSI Approved :: MIT License
Classifier: Programming Language :: Python :: 3
Classifier: Programming Language :: Python :: 3.6
License-File: LICENSE
Requires-Dist: numpy
Requires-Dist: pysam
Requires-Dist: pyfastx
Dynamic: author
Dynamic: author-email
Dynamic: classifier
Dynamic: description
Dynamic: description-content-type
Dynamic: download-url
Dynamic: home-page
Dynamic: keywords
Dynamic: license
Dynamic: license-file
Dynamic: requires-dist
Dynamic: summary
